labml_dashboard/__init__.py
labml_dashboard/__pycache__/__init__.cpython-37.pyc
labml_dashboard/app/package-lock.json
labml_dashboard/app/package.json
labml_dashboard/app/server/common/api.js
labml_dashboard/app/server/common/api_handler.js
labml_dashboard/app/server/common/cell.js
labml_dashboard/app/server/common/experiments.js
labml_dashboard/app/server/lib/io/io.js
labml_dashboard/app/server/lib/io/node.js
labml_dashboard/app/server/lib/io/static.js
labml_dashboard/app/server/server/api_server.js
labml_dashboard/app/server/server/app.js
labml_dashboard/app/server/server/browser.js
labml_dashboard/app/server/server/consts.js
labml_dashboard/app/server/server/jupyter.js
labml_dashboard/app/server/server/lab.js
labml_dashboard/app/server/server/run_nodejs.js
labml_dashboard/app/server/server/server.js
labml_dashboard/app/server/server/tensorboard.js
labml_dashboard/app/server/server/util.js
labml_dashboard/app/server/server/experiments/cache.js
labml_dashboard/app/ui/index.html
labml_dashboard/app/ui/css/style.css
labml_dashboard/app/ui/css/style.css.map
labml_dashboard/app/ui/images/dashboard_icon.png
labml_dashboard/app/ui/images/lab_icon.png
labml_dashboard/app/ui/js/common/api.js
labml_dashboard/app/ui/js/common/api_handler.js
labml_dashboard/app/ui/js/common/cell.js
labml_dashboard/app/ui/js/common/experiments.js
labml_dashboard/app/ui/js/lib/io/ajax.js
labml_dashboard/app/ui/js/lib/io/io.js
labml_dashboard/app/ui/js/lib/weya/router.js
labml_dashboard/app/ui/js/lib/weya/weya.js
labml_dashboard/app/ui/js/ui/app.js
labml_dashboard/app/ui/js/ui/cache.js
labml_dashboard/app/ui/js/ui/codemirror.js
labml_dashboard/app/ui/js/ui/configs.js
labml_dashboard/app/ui/js/ui/d3.js
labml_dashboard/app/ui/js/ui/diff_view.js
labml_dashboard/app/ui/js/ui/hljs.js
labml_dashboard/app/ui/js/ui/indicators.js
labml_dashboard/app/ui/js/ui/jsyaml.js
labml_dashboard/app/ui/js/ui/main.js
labml_dashboard/app/ui/js/ui/run_ui.js
labml_dashboard/app/ui/js/ui/run_view.js
labml_dashboard-0.4.87.dist-info/METADATA
labml_dashboard-0.4.87.dist-info/WHEEL
labml_dashboard-0.4.87.dist-info/top_level.txt
labml_dashboard-0.4.87.dist-info/RECORD
