Metadata-Version: 2.1
Name: labml-dashboard
Version: 0.4.87
Summary: Dashboard for Lab: Organize Machine Learning Experiments
Home-page: https://github.com/lab-ml/dashboard
Author: Varuna Jayasiri
Author-email: vpjayasiri@gmail.com
License: UNKNOWN
Project-URL: Documentation, https://lab-ml.com/
Keywords: machine learning
Platform: UNKNOWN
Classifier: Programming Language :: Python :: 3
Classifier: License :: OSI Approved :: MIT License
Classifier: Intended Audience :: Developers
Classifier: Intended Audience :: Science/Research
Classifier: Topic :: Scientific/Engineering
Classifier: Topic :: Scientific/Engineering :: Mathematics
Classifier: Topic :: Scientific/Engineering :: Artificial Intelligence
Classifier: Topic :: Software Development
Classifier: Topic :: Software Development :: Libraries
Classifier: Topic :: Software Development :: Libraries :: Python Modules
Requires-Dist: labml (>=0.4.87)
